probfit/version.py
probfit/statutil.py
probfit/oneshot.py
probfit/toy.py
probfit/funcutil.cpython-36m-i386-linux-gnu.so
probfit/_libstat.cpython-36m-i386-linux-gnu.so
probfit/probfit_warnings.py
probfit/pdf.cpython-36m-i386-linux-gnu.so
probfit/costfunc.cpython-36m-i386-linux-gnu.so
probfit/nputil.py
probfit/util.py
probfit/py23_compat.py
probfit/functor.cpython-36m-i386-linux-gnu.so
probfit/__init__.py
probfit/plotting.py
probfit/decorator.py
probfit-1.2.0.dist-info/WHEEL
probfit-1.2.0.dist-info/top_level.txt
probfit-1.2.0.dist-info/RECORD
probfit-1.2.0.dist-info/METADATA
probfit-1.2.0.dist-info/LICENSE
