Metadata-Version: 2.1
Name: probfit
Version: 1.2.0
Summary: Distribution Fitting/Regression Library
Home-page: https://github.com/scikit-hep/probfit
Author: Piti Ongmongkolkul
Author-email: piti118@gmail.com
Maintainer: Scikit-HEP
Maintainer-email: scikit-hep-admins@googlegroups.com
License: MIT
Platform: UNKNOWN
Classifier: Development Status :: 7 - Inactive
Classifier: Intended Audience :: Science/Research
Classifier: License :: OSI Approved :: MIT License
Classifier: Programming Language :: Python
Classifier: Programming Language :: Python :: 2
Classifier: Programming Language :: Python :: 2.7
Classifier: Programming Language :: Python :: 3
Classifier: Programming Language :: Python :: 3.5
Classifier: Programming Language :: Python :: 3.6
Classifier: Programming Language :: Python :: 3.7
Classifier: Programming Language :: Python :: 3.8
Classifier: Programming Language :: Python :: 3.9
Classifier: Topic :: Scientific/Engineering :: Mathematics
Classifier: Topic :: Scientific/Engineering :: Physics
Requires-Python: !=3.0.*,!=3.1.*,!=3.2.*,!=3.3.*,!=3.4.*,>=2.7
Requires-Dist: numpy
Requires-Dist: iminuit (<1.4) ; python_version < "3.5"
Requires-Dist: iminuit (<2) ; python_version >= "3.5"
Provides-Extra: dev
Requires-Dist: matplotlib (>=2.0) ; extra == 'dev'
Requires-Dist: pytest (>=4.6) ; extra == 'dev'
Requires-Dist: pytest-cov ; extra == 'dev'
Requires-Dist: pytest-mpl (<0.11) ; (python_version < "3.6") and extra == 'dev'
Requires-Dist: pytest-mpl ; (python_version >= "3.6") and extra == 'dev'
Provides-Extra: docs
Requires-Dist: ipython ; extra == 'docs'
Requires-Dist: sphinx ; extra == 'docs'
Requires-Dist: sphinx-rtd-theme ; extra == 'docs'
Provides-Extra: test
Requires-Dist: pytest (>=4.6) ; extra == 'test'
Requires-Dist: pytest-cov ; extra == 'test'
Requires-Dist: pytest-mpl (<0.11) ; (python_version < "3.6") and extra == 'test'
Requires-Dist: pytest-mpl ; (python_version >= "3.6") and extra == 'test'
